jaxlie/__init__.py
jaxlie/_base.py
jaxlie/_se2.py
jaxlie/_se3.py
jaxlie/_so2.py
jaxlie/_so3.py
jaxlie/py.typed
jaxlie/hints/__init__.py
jaxlie/manifold/__init__.py
jaxlie/manifold/_backprop.py
jaxlie/manifold/_deltas.py
jaxlie/manifold/_tree_utils.py
jaxlie/utils/__init__.py
jaxlie/utils/_utils.py
jaxlie-1.5.0.dist-info/licenses/LICENSE
jaxlie-1.5.0.dist-info/METADATA
jaxlie-1.5.0.dist-info/WHEEL
jaxlie-1.5.0.dist-info/top_level.txt
jaxlie-1.5.0.dist-info/RECORD
