Metadata-Version: 2.4
Name: jaxlie
Version: 1.5.0
Summary: Matrix Lie groups in JAX
Home-page: http://github.com/brentyi/jaxlie
Author: brentyi
Author-email: brentyi@berkeley.edu
License: MIT
Classifier: Programming Language :: Python :: 3.7
Classifier: Programming Language :: Python :: 3.8
Classifier: Programming Language :: Python :: 3.9
Classifier: Programming Language :: Python :: 3.10
Classifier: License :: OSI Approved :: MIT License
Classifier: Operating System :: OS Independent
Requires-Python: >=3.8
License-File: LICENSE
Requires-Dist: jax>=0.3.18
Requires-Dist: jax_dataclasses>=1.4.4
Requires-Dist: numpy
Requires-Dist: typing_extensions>=4.0.0
Requires-Dist: tyro
Provides-Extra: testing
Requires-Dist: mypy; extra == "testing"
Requires-Dist: jax!=0.3.19; extra == "testing"
Requires-Dist: flax; extra == "testing"
Requires-Dist: hypothesis[numpy]; extra == "testing"
Requires-Dist: pytest; extra == "testing"
Requires-Dist: pytest-xdist[psutil]; extra == "testing"
Requires-Dist: pytest-cov; extra == "testing"
Dynamic: author
Dynamic: author-email
Dynamic: classifier
Dynamic: description
Dynamic: description-content-type
Dynamic: home-page
Dynamic: license
Dynamic: license-file
Dynamic: provides-extra
Dynamic: requires-dist
Dynamic: requires-python
Dynamic: summary
